{"swagger":"2.0","info":{"title":"Boxobox-API","version":"1.0.0","description":"api for boxobox project"},"paths":{"/api/luminosities/{id}":{"delete":{"tags":["Luminosities"],"summary":"delete a luminosity ","consumes":["application/json"],"produces":["application/json"],"parameters":[{"name":"id","in":"path","required":true,"type":"string","description":"id of the luminosity "}]},"get":{"tags":["Luminosities"],"summary":"request luminosity by id ","consumes":["application/json"],"produces":["application/json"],"parameters":[{"name":"id","in":"path","required":true,"type":"string","description":"id of the luminosity "}]}},"/api/luminosities":{"get":{"tags":["Luminosities"],"summary":"request all luminosities record ","consumes":["application/json"],"produces":["application/json"],"parameters":[{"name":"after","in":"query","required":false,"type":"query","description":"date you want record to be after "},{"name":"before","in":"query","required":false,"type":"query","description":"date you want record to be before "},{"name":"orderDate","in":"query","required":false,"type":"query","description":"order results by date [ASC, DESC] "}]},"post":{"tags":["Luminosities"],"summary":"create a luminosity ","consumes":["application/json"],"produces":["application/json"],"parameters":[{"in":"body","name":"body","description":"create a luminosity ","required":true,"schema":{"$ref":"#/definitions/PostApiLuminosities"}}]}},"/api/luminosities/last":{"get":{"tags":["Luminosities"],"summary":"get the last measure ","consumes":["application/json"],"produces":["application/json"],"parameters":[]}},"/api/messages":{"get":{"tags":["Messages"],"summary":"request all messages ","consumes":["application/json"],"produces":["application/json"],"parameters":[]},"post":{"tags":["Messages"],"summary":"create a message ","consumes":["application/json"],"produces":["application/json"],"parameters":[{"in":"body","name":"body","description":"create a message ","required":true,"schema":{"$ref":"#/definitions/PostApiMessages"}}]}},"/api/messages/room/{id}":{"get":{"tags":["Messages"],"summary":"request messages by chat id ","consumes":["application/json"],"produces":["application/json"],"parameters":[{"name":"id","in":"path","required":true,"type":"string","description":"id of the chat "}]}},"/api/noises/{id}":{"delete":{"tags":["Noises"],"summary":"delete a noise ","consumes":["application/json"],"produces":["application/json"],"parameters":[{"name":"id","in":"path","required":true,"type":"string","description":"id of the noise "}]},"get":{"tags":["Noises"],"summary":"request noise by id ","consumes":["application/json"],"produces":["application/json"],"parameters":[{"name":"id","in":"path","required":true,"type":"string","description":"id of the noise "}]}},"/api/noises":{"get":{"tags":["Noises"],"summary":"request all noises record ","consumes":["application/json"],"produces":["application/json"],"parameters":[{"name":"after","in":"query","required":false,"type":"query","description":"date you want record to be after "},{"name":"before","in":"query","required":false,"type":"query","description":"date you want record to be before "},{"name":"orderDate","in":"query","required":false,"type":"query","description":"order results by date [ASC, DESC] "}]},"post":{"tags":["Noises"],"summary":"create a noise ","consumes":["application/json"],"produces":["application/json"],"parameters":[{"in":"body","name":"body","description":"create a noise ","required":true,"schema":{"$ref":"#/definitions/PostApiNoises"}}]}},"/api/noises/last":{"get":{"tags":["Noises"],"summary":"get the last measure ","consumes":["application/json"],"produces":["application/json"],"parameters":[]}},"/api/temperatures/{id}":{"delete":{"tags":["Temperatures"],"summary":"delete a temperature ","consumes":["application/json"],"produces":["application/json"],"parameters":[{"name":"id","in":"path","required":true,"type":"string","description":"id of the temperature "}]},"get":{"tags":["Temperatures"],"summary":"request temperature by id ","consumes":["application/json"],"produces":["application/json"],"parameters":[{"name":"id","in":"path","required":true,"type":"string","description":"id of the temperature "}]}},"/api/temperatures":{"get":{"tags":["Temperatures"],"summary":"request all temperatures record ","consumes":["application/json"],"produces":["application/json"],"parameters":[{"name":"after","in":"query","required":false,"type":"query","description":"date you want record to be after "},{"name":"before","in":"query","required":false,"type":"query","description":"date you want record to be before "},{"name":"orderDate","in":"query","required":false,"type":"query","description":"order results by date [ASC, DESC] "}]},"post":{"tags":["Temperatures"],"summary":"create a temperature ","consumes":["application/json"],"produces":["application/json"],"parameters":[{"in":"body","name":"body","description":"create a temperature ","required":true,"schema":{"$ref":"#/definitions/PostApiTemperatures"}}]}},"/api/temperatures/last":{"get":{"tags":["Temperatures"],"summary":"get the last measure ","consumes":["application/json"],"produces":["application/json"],"parameters":[]}},"/api/users/{id}":{"delete":{"tags":["Users"],"summary":"delete a user ","consumes":["application/json"],"produces":["application/json"],"parameters":[{"name":"id","in":"path","required":true,"type":"string","description":"id of the user "}]},"get":{"tags":["Users"],"summary":"request user by id ","consumes":["application/json"],"produces":["application/json"],"parameters":[{"name":"id","in":"path","required":true,"type":"string","description":"id of the user "}]},"put":{"tags":["Users"],"summary":"update a user ","consumes":["application/json"],"produces":["application/json"],"parameters":[{"name":"id","in":"path","required":true,"type":"string","description":"id of the user "},{"in":"body","name":"body","description":"update a user ","required":false,"schema":{"$ref":"#/definitions/PutApiUsersId"}}]}},"/api/users":{"get":{"tags":["Users"],"summary":"request all users ","consumes":["application/json"],"produces":["application/json"],"parameters":[{"name":"username","in":"query","required":false,"type":"query","description":"username of user "},{"name":"email","in":"query","required":false,"type":"query","description":"email of user "},{"name":"gender","in":"query","required":false,"type":"query","description":"male of female "}]},"post":{"tags":["Users"],"summary":"create a user ","consumes":["application/json"],"produces":["application/json"],"parameters":[{"in":"body","name":"body","description":"create a user ","required":true,"schema":{"$ref":"#/definitions/PostApiUsers"}}]}},"/api/users/login":{"post":{"tags":["Users"],"summary":"login a user ","consumes":["application/json"],"produces":["application/json"],"parameters":[{"in":"body","name":"body","description":"login a user ","required":true,"schema":{"$ref":"#/definitions/PostApiUsersLogin"}}]}}},"definitions":{"PostApiMessages":{"properties":{"username":{"type":"string","description":"username of the User. "},"roomId":{"type":"string","description":"id of the room. "},"message":{"type":"string","description":"content of the message. "}},"required":["username","roomId","message"]},"GetApiMessagesRoomId":{"properties":{"id":{"type":"string","description":"id of the chat "}},"required":["id"]},"DeleteApiTemperaturesId":{"properties":{"id":{"type":"string","description":"id of the temperature "}},"required":["id"]},"GetApiTemperaturesId":{"properties":{"id":{"type":"string","description":"id of the temperature "}},"required":["id"]},"GetApiTemperatures":{"properties":{"after":{"type":"query","description":"date you want record to be after "},"before":{"type":"query","description":"date you want record to be before "},"orderDate":{"type":"query","description":"order results by date [ASC, DESC] "}},"required":[]},"PostApiTemperatures":{"properties":{"value":{"type":"number","description":"temperature measure "},"date":{"type":"date","description":"date of the measure "}},"required":["value","date"]},"DeleteApiUsersId":{"properties":{"id":{"type":"string","description":"id of the user "}},"required":["id"]},"GetApiUsersId":{"properties":{"id":{"type":"string","description":"id of the user "}},"required":["id"]},"PutApiUsersId":{"properties":{"id":{"type":"string","description":"id of the user "},"email":{"type":"string","description":"email of the User. "},"username":{"type":"string","description":"username of the User. "},"firstname":{"type":"string","description":"Optional Firstname of the User. "},"lastname":{"type":"string","description":"Optional Lastname of the User. "}},"required":["id","email","username","firstname","lastname"]},"GetApiUsers":{"properties":{"username":{"type":"query","description":"username of user "},"email":{"type":"query","description":"email of user "},"gender":{"type":"query","description":"male of female "}},"required":[]},"PostApiUsers":{"properties":{"email":{"type":"string","description":"email of the User. "},"username":{"type":"string","description":"username of the User. "},"firstname":{"type":"string","description":"Optional Firstname of the User. "},"lastname":{"type":"string","description":"Optional Lastname of the User. "}},"required":["email","username","firstname","lastname"]},"PostApiUsersLogin":{"properties":{"email":{"type":"string","description":"or username of the User. "},"password":{"type":"string","description":"of the User. "}},"required":["email","password"]},"DeleteApiNoisesId":{"properties":{"id":{"type":"string","description":"id of the noise "}},"required":["id"]},"GetApiNoisesId":{"properties":{"id":{"type":"string","description":"id of the noise "}},"required":["id"]},"GetApiNoises":{"properties":{"after":{"type":"query","description":"date you want record to be after "},"before":{"type":"query","description":"date you want record to be before "},"orderDate":{"type":"query","description":"order results by date [ASC, DESC] "}},"required":[]},"PostApiNoises":{"properties":{"value":{"type":"number","description":"noise measure "},"date":{"type":"date","description":"date of the measure "}},"required":["value","date"]},"DeleteApiLuminositiesId":{"properties":{"id":{"type":"string","description":"id of the luminosity "}},"required":["id"]},"GetApiLuminositiesId":{"properties":{"id":{"type":"string","description":"id of the luminosity "}},"required":["id"]},"GetApiLuminosities":{"properties":{"after":{"type":"query","description":"date you want record to be after "},"before":{"type":"query","description":"date you want record to be before "},"orderDate":{"type":"query","description":"order results by date [ASC, DESC] "}},"required":[]},"PostApiLuminosities":{"properties":{"value":{"type":"number","description":"luminosity measure "},"date":{"type":"date","description":"date of the measure "}},"required":["value","date"]}}}